aioflowdock/__init__.py
aioflowdock/flowdock.py
aioflowdock/stream.py
aioflowdock-0.2.2.dist-info/LICENSE
aioflowdock-0.2.2.dist-info/METADATA
aioflowdock-0.2.2.dist-info/WHEEL
aioflowdock-0.2.2.dist-info/top_level.txt
aioflowdock-0.2.2.dist-info/RECORD
