Metadata-Version: 2.1
Name: aioflowdock
Version: 0.2.2
Summary: UNKNOWN
Home-page: https://github.com/LFLab/aio-flowdock
Author: Lanfon
Author-email: lanfon72@gmail.com
License: UNKNOWN
Platform: UNKNOWN
Classifier: Development Status :: 3 - Alpha
Classifier: Intended Audience :: Developers
Classifier: License :: OSI Approved :: MIT License
Classifier: Operating System :: OS Independent
Classifier: Programming Language :: Python :: 3.6
Classifier: Programming Language :: Python :: 3.7
Requires-Python: >=3.6
Requires-Dist: aiohttp (>=3.*)
Requires-Dist: pyee (>=6.*)
Requires-Dist: aiohttp-sse-client
